ldobserve/__init__.py
ldobserve/config.py
launchdarkly_observability-0.0.0.dist-info/METADATA
launchdarkly_observability-0.0.0.dist-info/WHEEL
launchdarkly_observability-0.0.0.dist-info/entry_points.txt
launchdarkly_observability-0.0.0.dist-info/RECORD
