Metadata-Version: 2.3
Name: launchdarkly-observability
Version: 0.0.0
Summary: LaunchDarkly Observability for Python
License: Apache-2.0
Author: LaunchDarkly Authors
Author-email: dev@launchdarkly.com
Requires-Python: >=3.9,<4
Classifier: Intended Audience :: Developers
Classifier: License :: OSI Approved :: Apache Software License
Classifier: Operating System :: OS Independent
Classifier: Programming Language :: Python :: 3
Classifier: Programming Language :: Python :: 3.8
Classifier: Programming Language :: Python :: 3.9
Classifier: Programming Language :: Python :: 3.10
Classifier: Programming Language :: Python :: 3.11
Classifier: Programming Language :: Python :: 3.12
Classifier: Topic :: Software Development
Classifier: Topic :: Software Development :: Libraries
Provides-Extra: dev
Requires-Dist: ariadne-codegen (>=0.14.0,<0.15.0)
Requires-Dist: azure-functions (>=1) ; extra == "dev"
Requires-Dist: black (>=24) ; extra == "dev"
Requires-Dist: blinker (>=1) ; extra == "dev"
Requires-Dist: django (>=4) ; extra == "dev"
Requires-Dist: fastapi (>=0) ; extra == "dev"
Requires-Dist: flask (>=3) ; extra == "dev"
Requires-Dist: functions-framework (>=3) ; extra == "dev"
Requires-Dist: loguru (>=0) ; extra == "dev"
Requires-Dist: opentelemetry-api (==1.34.1)
Requires-Dist: opentelemetry-exporter-otlp-proto-grpc (==1.34.1)
Requires-Dist: opentelemetry-instrumentation (==0.55b1)
Requires-Dist: opentelemetry-instrumentation-aiohttp-client (==0.55b1)
Requires-Dist: opentelemetry-instrumentation-aiohttp-server (==0.55b1)
Requires-Dist: opentelemetry-instrumentation-anthropic (==0.40.14)
Requires-Dist: opentelemetry-instrumentation-bedrock (==0.40.14)
Requires-Dist: opentelemetry-instrumentation-boto (==0.55b1)
Requires-Dist: opentelemetry-instrumentation-boto3sqs (==0.55b1)
Requires-Dist: opentelemetry-instrumentation-celery (==0.55b1)
Requires-Dist: opentelemetry-instrumentation-chromadb (==0.40.14)
Requires-Dist: opentelemetry-instrumentation-cohere (==0.40.14)
Requires-Dist: opentelemetry-instrumentation-django (==0.55b1)
Requires-Dist: opentelemetry-instrumentation-fastapi (==0.55b1)
Requires-Dist: opentelemetry-instrumentation-flask (==0.55b1)
Requires-Dist: opentelemetry-instrumentation-grpc (==0.55b1)
Requires-Dist: opentelemetry-instrumentation-haystack (==0.40.14)
Requires-Dist: opentelemetry-instrumentation-httpx (==0.55b1)
Requires-Dist: opentelemetry-instrumentation-jinja2 (==0.55b1)
Requires-Dist: opentelemetry-instrumentation-langchain (==0.40.14)
Requires-Dist: opentelemetry-instrumentation-llamaindex (==0.40.14)
Requires-Dist: opentelemetry-instrumentation-logging (==0.55b1)
Requires-Dist: opentelemetry-instrumentation-openai (==0.40.14)
Requires-Dist: opentelemetry-instrumentation-pinecone (==0.40.14)
Requires-Dist: opentelemetry-instrumentation-psycopg (==0.55b1)
Requires-Dist: opentelemetry-instrumentation-psycopg2 (==0.55b1)
Requires-Dist: opentelemetry-instrumentation-qdrant (==0.40.14)
Requires-Dist: opentelemetry-instrumentation-redis (==0.55b1)
Requires-Dist: opentelemetry-instrumentation-replicate (==0.40.14)
Requires-Dist: opentelemetry-instrumentation-requests (==0.55b1)
Requires-Dist: opentelemetry-instrumentation-sqlalchemy (==0.55b1)
Requires-Dist: opentelemetry-instrumentation-sqlite3 (==0.55b1)
Requires-Dist: opentelemetry-instrumentation-starlette (==0.55b1)
Requires-Dist: opentelemetry-instrumentation-system-metrics (==0.55b1)
Requires-Dist: opentelemetry-instrumentation-transformers (==0.40.14)
Requires-Dist: opentelemetry-instrumentation-urllib (==0.55b1)
Requires-Dist: opentelemetry-instrumentation-urllib3 (==0.55b1)
Requires-Dist: opentelemetry-instrumentation-vertexai (==0.40.14)
Requires-Dist: opentelemetry-instrumentation-watsonx (==0.40.14)
Requires-Dist: opentelemetry-instrumentation-weaviate (==0.40.14)
Requires-Dist: opentelemetry-instrumentation-wsgi (==0.55b1)
Requires-Dist: opentelemetry-proto (==1.34.1)
Requires-Dist: opentelemetry-sdk (==1.34.1)
Requires-Dist: orjson (==3.9.15) ; extra == "dev"
Requires-Dist: pytest (>=8) ; extra == "dev"
Requires-Dist: pytest-asyncio (>=0) ; extra == "dev"
Requires-Dist: pytest-cov (>=5) ; extra == "dev"
Requires-Dist: pytest-mock (>=3) ; extra == "dev"
Requires-Dist: requests (>=2.31.0)
Requires-Dist: urllib3 (>=2.2.1)
